centrex_trajectories/__init__.py
centrex_trajectories/beamline_objects.py
centrex_trajectories/common_types.py
centrex_trajectories/data_structures.py
centrex_trajectories/numba_functions.py
centrex_trajectories/particles.py
centrex_trajectories/polynomials.py
centrex_trajectories/propagation.py
centrex_trajectories/propagation_ballistic.py
centrex_trajectories/propagation_linear.py
centrex_trajectories/propagation_ode.py
centrex_trajectories/propagation_options.py
centrex_trajectories/py.typed
centrex_trajectories/random_generation.py
centrex_trajectories/utils.py
centrex_trajectories/visualization.py
centrex_trajectories/saved_data/stark_poly.pkl
centrex_trajectories-0.3.2.dist-info/METADATA
centrex_trajectories-0.3.2.dist-info/WHEEL
centrex_trajectories-0.3.2.dist-info/licenses/LICENSE
centrex_trajectories-0.3.2.dist-info/RECORD
