Metadata-Version: 2.4
Name: centrex-trajectories
Version: 0.3.2
Author-email: ograsdijk <o.grasdijk@gmail.com>
License-Expression: MIT
License-File: LICENSE
Requires-Python: >3.10
Requires-Dist: joblib<2,>=1.2.0
Requires-Dist: matplotlib<4,>=3.10.1
Requires-Dist: numba<0.62,>=0.61.2
Requires-Dist: numpy<3,>=2.2.5
Requires-Dist: scipy<2,>=1.15.2
